examples/__init__.py
examples/calc_token_consumption.py
examples/custom_element_type.py
examples/custom_encoding_strategy.py
examples/getting_started.py
examples/save_and_load_prompts.py
promptex/__init__.py
promptex/promptex.py
promptex/elements/__init__.py
promptex/elements/constraint.py
promptex/elements/context.py
promptex/elements/element.py
promptex/elements/element_type.py
promptex/elements/input_data.py
promptex/elements/instruction.py
promptex/elements/output_format.py
promptex/elements/role.py
promptex/encoding_strategy/__init__.py
promptex/encoding_strategy/base_encoding_strategy.py
promptex/encoding_strategy/simple_csv_encoding_strategy.py
promptex/encoding_strategy/simple_html_encoding_strategy.py
promptex/encoding_strategy/simple_json_encoding_strategy.py
promptex/encoding_strategy/simple_json_schema_encoding_strategy.py
promptex/encoding_strategy/simple_markdown_encoding_strategy.py
promptex/encoding_strategy/simple_text_encoding_strategy.py
promptex/encoding_strategy/simple_xml_encoding_strategy.py
promptex/encoding_strategy/simple_yaml_encoding_strategy.py
promptex-0.1.0.dist-info/LICENSE
promptex-0.1.0.dist-info/METADATA
promptex-0.1.0.dist-info/WHEEL
promptex-0.1.0.dist-info/top_level.txt
promptex-0.1.0.dist-info/RECORD
