Metadata-Version: 2.1
Name: promptex
Version: 0.1.0
Summary: Efficiently manage prompts used as input for GPT
Home-page: https://github.com/rinov/promptex
Author: rinov
Author-email: rinov@rinov.jp
License: MIT
Keywords: gpt,prompt,promptex
Platform: UNKNOWN
Classifier: Programming Language :: Python :: 3
Requires-Python: >=3.8.0
Requires-Dist: tiktoken (>=0.3.3)
